AUTHORS
CHANGELOG
LICENSE
MANIFEST.in
README.rst
manage.py
requirements.txt
setup.py
testsettings.py
django_netfields.egg-info/PKG-INFO
django_netfields.egg-info/SOURCES.txt
django_netfields.egg-info/dependency_links.txt
django_netfields.egg-info/not-zip-safe
django_netfields.egg-info/requires.txt
django_netfields.egg-info/top_level.txt
netfields/__init__.py
netfields/apps.py
netfields/compat.py
netfields/fields.py
netfields/forms.py
netfields/functions.py
netfields/lookups.py
netfields/mac.py
netfields/managers.py
netfields/models.py
netfields/psycopg2_types.py
netfields/psycopg3_types.py
netfields/rest_framework.py
test/__init__.py
test/__init__.pyc
test/models.py
test/models.pyc
test/tests/__init__.py
test/tests/__init__.pyc
test/tests/test_form_fields.py
test/tests/test_form_fields.pyc
test/tests/test_functions.py
test/tests/test_functions.pyc
test/tests/test_rest_framework_fields.py
test/tests/test_rest_framework_fields.pyc
test/tests/test_sql_fields.py
test/tests/test_sql_fields.pyc