Metadata-Version: 2.1
Name: django-netfields
Version: 1.3.1
Summary: Django PostgreSQL netfields implementation
Home-page: https://github.com/jimfunk/django-postgresql-netfields
Author: James Oakley
Author-email: jfunk@funktronics.ca
License: BSD
Classifier: Development Status :: 4 - Beta
Classifier: Environment :: Web Environment
Classifier: Framework :: Django
Classifier: Intended Audience :: Developers
Classifier: License :: OSI Approved :: BSD License
Classifier: Operating System :: OS Independent
Classifier: Programming Language :: Python
Classifier: Topic :: Utilities
License-File: LICENSE
License-File: AUTHORS
